{"scoreboard": [{"wins": 0, "points": 0, "losses": 0, "draws": 0, "team": "Team Diego"}, {"wins": 0, "points": 0, "losses": 0, "draws": 0, "team": "Team Washington"}, {"wins": 0, "points": 0, "losses": 0, "draws": 0, "team": "Team Tim"}, {"wins": 0, "points": 0, "losses": 0, "draws": 0, "team": "Team Adan"}, {"wins": 0, "points": 0, "losses": 0, "draws": 0, "team": "Team Maddie"}, {"wins": 0, "points": 0, "losses": 0, "draws": 0, "team": "Team Lauren"}, {"wins": 0, "points": 0, "losses": 0, "draws": 0, "team": "Team Marvin"}, {"wins": 0, "points": 0, "losses": 0, "draws": 0, "team": "Team Carlos"}, {"wins": 0, "points": 0, "losses": 0, "draws": 0, "team": "Team Hiller"}, {"wins": 0, "points": 0, "losses": 0, "draws": 0, "team": "Team Geno"}, {"wins": 0, "points": 0, "losses": 0, "draws": 0, "team": "Team Chris"}], "fixtures": {"1": [{"winner": "NA", "score_team1": "", "team1": "Team Diego", "team2": "Team Washington", "score_team2": ""}, {"winner": "NA", "score_team1": "", "team1": "Team Tim", "team2": "Team Adan", "score_team2": ""}, {"winner": "NA", "score_team1": "", "team1": "Team Maddie", "team2": "Team Lauren", "score_team2": ""}, {"winner": "NA", "score_team1": "", "team1": "Team Marvin", "team2": "Team Carlos", "score_team2": ""}, {"winner": "NA", "team1": "Team Hiller", "team2": "Team Geno", "team3": "Team Chris", "score_team1": "", "score_team3": "", "score_team2": ""}], "3": [{"winner": "NA", "score_team1": "", "team1": "Team Tim", "team2": "Team Washington", "score_team2": ""}, {"winner": "NA", "score_team1": "", "team1": "Team Geno", "team2": "Team Adan", "score_team2": ""}, {"winner": "NA", "team1": "Team Maddie", "team2": "Team Lauren", "team3": "Team Diego", "score_team1": "", "score_team3": "", "score_team2": ""}, {"winner": "NA", "score_team1": "", "team1": "Team Hiller", "team2": "Team Carlos", "score_team2": ""}, {"winner": "NA", "score_team1": "", "team1": "Team Chris", "team2": "Team Marvin", "score_team2": ""}], "2": [{"winner": "NA", "score_team1": "", "team1": "Team Diego", "team2": "Team Tim", "score_team2": ""}, {"winner": "NA", "score_team1": "", "team1": "Team Washington", "team2": "Team Adan", "score_team2": ""}, {"winner": "NA", "score_team1": "", "team1": "Team Hiller", "team2": "Team Chris", "score_team2": ""}, {"winner": "NA", "score_team1": "", "team1": "Team Maddie", "team2": "Team Marvin", "score_team2": ""}, {"winner": "NA", "team1": "Team Carlos", "team2": "Team Geno", "team3": "Team Lauren", "score_team1": "", "score_team3": "", "score_team2": ""}], "5": [{"winner": "NA", "score_team1": "", "team1": "Team Washington", "team2": "Team Hiller", "score_team2": ""}, {"winner": "NA", "score_team1": "", "team1": "Team Maddie", "team2": "Team Chris", "score_team2": ""}, {"winner": "NA", "team1": "Team Adan", "team2": "Team Diego", "team3": "Team Marvin", "score_team1": "", "score_team3": "", "score_team2": ""}, {"winner": "NA", "score_team1": "", "team1": "Team Geno", "team2": "Team Carlos", "score_team2": ""}, {"winner": "NA", "score_team1": "", "team1": "Team Tim", "team2": "Team Lauren", "score_team2": ""}], "4": [{"winner": "NA", "team1": "Team Washington", "team2": "Team Lauren", "team3": "Team Adan", "score_team1": "", "score_team3": "", "score_team2": ""}, {"winner": "NA", "score_team1": "", "team1": "Team Hiller", "team2": "Team Diego", "score_team2": ""}, {"winner": "NA", "score_team1": "", "team1": "Team Marvin", "team2": "Team Lauren", "score_team2": ""}, {"winner": "NA", "score_team1": "", "team1": "Team Tim", "team2": "Team Chris", "score_team2": ""}, {"winner": "NA", "score_team1": "", "team1": "Team Geno", "team2": "Team Maddie", "score_team2": ""}]}, "version": 0, "playoffs": [{"winner": "", "score_team1": "", "team1": "TBD", "team2": "TBD", "score_team2": ""}, {"winner": "", "score_team1": "", "team1": "TBD", "team2": "TBD", "score_team2": ""}, {"winner": "", "score_team1": "", "team1": "TBD", "team2": "TBD", "score_team2": ""}, {"winner": "", "score_team1": "", "team1": "TBD", "team2": "TBD", "score_team2": ""}, {"winner": "", "score_team1": "", "team1": "TBD", "team2": "TBD", "score_team2": ""}], "teams": ["Team Diego", "Team Washington", "Team Tim", "Team Adan", "Team Maddie", "Team Lauren", "Team Marvin", "Team Carlos", "Team Hiller", "Team Geno", "Team Chris"]}